RestShizhan/README.md
RestShizhan/__init__.py
RestShizhan/__main__.py
RestShizhan/file.epub
RestShizhan/index.html
RestShizhan/css/__init__.py
RestShizhan/css/annotations.css
RestShizhan/css/main.css
RestShizhan/css/normalize.css
RestShizhan/css/popup.css
RestShizhan/font/__init__.py
RestShizhan/font/fontello.eot
RestShizhan/font/fontello.svg
RestShizhan/font/fontello.ttf
RestShizhan/font/fontello.woff
RestShizhan/img/__init__.py
RestShizhan/img/annotator-glyph-sprite.png
RestShizhan/img/annotator-icon-sprite.png
RestShizhan/img/apple-touch-icon.png
RestShizhan/img/cancelfullscreen.png
RestShizhan/img/close.png
RestShizhan/img/fullscreen.png
RestShizhan/img/loader.gif
RestShizhan/img/menu-icon.png
RestShizhan/img/save.png
RestShizhan/img/saved.png
RestShizhan/img/settings-s.png
RestShizhan/img/settings.png
RestShizhan/img/star.png
RestShizhan/js/__init__.py
RestShizhan/js/epub.js
RestShizhan/js/epub.min.js
RestShizhan/js/epub.min.map
RestShizhan/js/hooks.min.js
RestShizhan/js/hooks.min.map
RestShizhan/js/reader.js
RestShizhan/js/reader.js.map
RestShizhan/js/reader.min.js
RestShizhan/js/reader.min.map
RestShizhan/js/hooks/__init__.py
RestShizhan/js/hooks/extensions/__init__.py
RestShizhan/js/hooks/extensions/highlight.js
RestShizhan/js/libs/__init__.py
RestShizhan/js/libs/jquery.min.js
RestShizhan/js/libs/localforage.min.js
RestShizhan/js/libs/screenfull.js
RestShizhan/js/libs/screenfull.min.js
RestShizhan/js/libs/zip.min.js
RestShizhan/js/plugins/__init__.py
RestShizhan/js/plugins/hypothesis.js
RestShizhan/js/plugins/search.js
rest_shizhan-2024.3.2.0.dist-info/METADATA
rest_shizhan-2024.3.2.0.dist-info/WHEEL
rest_shizhan-2024.3.2.0.dist-info/entry_points.txt
rest_shizhan-2024.3.2.0.dist-info/top_level.txt
rest_shizhan-2024.3.2.0.dist-info/RECORD
